svnbranch/__init__.py
svnbranch/svnbranch.py
svnbranch-1.1.dist-info/DESCRIPTION.rst
svnbranch-1.1.dist-info/METADATA
svnbranch-1.1.dist-info/RECORD
svnbranch-1.1.dist-info/WHEEL
svnbranch-1.1.dist-info/entry_points.txt
svnbranch-1.1.dist-info/metadata.json
svnbranch-1.1.dist-info/top_level.txt
