Metadata-Version: 2.0
Name: svnbranch
Version: 1.1
Summary: A simple svn branch tool with externals support
Home-page: https://github.com/fyrestone/svnbranch
Author: fyrestone
Author-email: fyrestone@outlook.com
License: MIT License
Keywords: svn branch external generic utility
Platform: All
Classifier: Development Status :: 5 - Production/Stable
Classifier: Intended Audience :: Developers
Classifier: License :: OSI Approved :: MIT License
Classifier: Natural Language :: English
Classifier: Operating System :: OS Independent
Classifier: Programming Language :: Python :: 2
Classifier: Programming Language :: Python :: 3
Classifier: Topic :: Software Development :: Libraries
Classifier: Topic :: Utilities
Requires-Dist: gevent
Requires-Dist: url-normalize
Requires-Dist: six
